hyros/__cli__.py
hyros/__init__.py
hyros/_version.py
hyros/conf/__init__.py
hyros/conf/about/hyros.yaml
hyros/py.typed
hyfi_ros-0.1.0.dist-info/LICENSE
hyfi_ros-0.1.0.dist-info/METADATA
hyfi_ros-0.1.0.dist-info/WHEEL
hyfi_ros-0.1.0.dist-info/entry_points.txt
hyfi_ros-0.1.0.dist-info/RECORD
